django_migration_linter/__init__.py
django_migration_linter/cache.py
django_migration_linter/constants.py
django_migration_linter/migration_linter.py
django_migration_linter/operations.py
django_migration_linter/utils.py
django_migration_linter/management/__init__.py
django_migration_linter/management/utils.py
django_migration_linter/management/commands/__init__.py
django_migration_linter/management/commands/lintmigrations.py
django_migration_linter/management/commands/makemigrations.py
django_migration_linter/sql_analyser/__init__.py
django_migration_linter/sql_analyser/analyser.py
django_migration_linter/sql_analyser/base.py
django_migration_linter/sql_analyser/mysql.py
django_migration_linter/sql_analyser/postgresql.py
django_migration_linter/sql_analyser/sqlite.py
django_migration_linter-5.1.0.dist-info/LICENSE
django_migration_linter-5.1.0.dist-info/METADATA
django_migration_linter-5.1.0.dist-info/WHEEL
django_migration_linter-5.1.0.dist-info/top_level.txt
django_migration_linter-5.1.0.dist-info/RECORD
