Metadata-Version: 2.1
Name: django-migration-linter
Version: 5.1.0
Summary: Detect backward incompatible migrations for your django project
Author-email: 3YOURMIND GmbH <fb@3yourmind.com>
Maintainer-email: David Wobrock <david.wobrock@gmail.com>
Project-URL: Changelog, https://github.com/3YOURMIND/django-migration-linter/blob/main/CHANGELOG.md
Project-URL: Repository, https://github.com/3YOURMIND/django-migration-linter
Keywords: django,migration,lint,linter,database,backward,compatibility
Classifier: Development Status :: 5 - Production/Stable
Classifier: Intended Audience :: Developers
Classifier: Environment :: Web Environment
Classifier: Framework :: Django
Classifier: Framework :: Django :: 3.2
Classifier: Framework :: Django :: 4.0
Classifier: Framework :: Django :: 4.1
Classifier: Framework :: Django :: 4.2
Classifier: Framework :: Django :: 5.0
Classifier: Programming Language :: Python
Classifier: Programming Language :: Python :: 3
Classifier: Programming Language :: Python :: 3.7
Classifier: Programming Language :: Python :: 3.8
Classifier: Programming Language :: Python :: 3.9
Classifier: Programming Language :: Python :: 3.10
Classifier: Programming Language :: Python :: 3.11
Classifier: Programming Language :: Python :: 3.12
Requires-Python: >=3.7
License-File: LICENSE
Requires-Dist: django>=2.2
Requires-Dist: appdirs>=1.4.3
Requires-Dist: toml>=0.10.2
Provides-Extra: test
Requires-Dist: tox>=4.6.3; extra == "test"
Requires-Dist: mysqlclient>=2.1.1; extra == "test"
Requires-Dist: psycopg2>=2.9.6; extra == "test"
Requires-Dist: django_add_default_value>=0.4.0; extra == "test"
Requires-Dist: coverage>=7.2.7; extra == "test"
